{
  "sophistication": 0.592,
  "profile": "scripted_bot",
  "length": 15,
  "total_time": 57.7,
  "steps": [
    {
      "t": 5.8,
      "cmd": "cat /proc/version",
      "ttp": "T1082",
      "recon": 1,
      "priv_esc": 0,
      "cred_access": 0,
      "lateral": 0,
      "suspicious_tools": 0,
      "exfil": 0,
      "profile": "scripted_bot"
    },
    {
      "t": 9.0,
      "cmd": "uname -a",
      "ttp": "T1082",
      "recon": 2,
      "priv_esc": 0,
      "cred_access": 0,
      "lateral": 0,
      "suspicious_tools": 0,
      "exfil": 0,
      "profile": "scripted_bot"
    },
    {
      "t": 10.4,
      "cmd": "id",
      "ttp": "T1082",
      "recon": 3,
      "priv_esc": 0,
      "cred_access": 0,
      "lateral": 0,
      "suspicious_tools": 0,
      "exfil": 0,
      "profile": "scripted_bot"
    },
    {
      "t": 13.4,
      "cmd": "ip addr",
      "ttp": "T1082",
      "recon": 4,
      "priv_esc": 0,
      "cred_access": 0,
      "lateral": 0,
      "suspicious_tools": 0,
      "exfil": 0,
      "profile": "scripted_bot"
    },
    {
      "t": 16.1,
      "cmd": "cat ~/.ssh/id_rsa",
      "ttp": "T1003",
      "recon": 4,
      "priv_esc": 0,
      "cred_access": 1,
      "lateral": 0,
      "suspicious_tools": 0,
      "exfil": 0,
      "profile": "scripted_bot"
    },
    {
      "t": 22.4,
      "cmd": "cat /etc/passwd",
      "ttp": "T1082",
      "recon": 5,
      "priv_esc": 0,
      "cred_access": 1,
      "lateral": 0,
      "suspicious_tools": 0,
      "exfil": 0,
      "profile": "scripted_bot"
    },
    {
      "t": 36.8,
      "cmd": "find / -name '*.conf' 2>/dev/null | head -5",
      "ttp": "T1082",
      "recon": 6,
      "priv_esc": 0,
      "cred_access": 1,
      "lateral": 0,
      "suspicious_tools": 0,
      "exfil": 0,
      "profile": "scripted_bot"
    },
    {
      "t": 38.8,
      "cmd": "find / -name '*.conf' 2>/dev/null | head -5",
      "ttp": "T1082",
      "recon": 7,
      "priv_esc": 0,
      "cred_access": 1,
      "lateral": 0,
      "suspicious_tools": 0,
      "exfil": 0,
      "profile": "scripted_bot"
    },
    {
      "t": 44.0,
      "cmd": "net use \\\\10.20.20.40\\c$",
      "ttp": "T1021",
      "recon": 7,
      "priv_esc": 0,
      "cred_access": 1,
      "lateral": 1,
      "suspicious_tools": 0,
      "exfil": 0,
      "profile": "scripted_bot"
    },
    {
      "t": 44.8,
      "cmd": "ls -la /home",
      "ttp": "T1082",
      "recon": 8,
      "priv_esc": 0,
      "cred_access": 1,
      "lateral": 1,
      "suspicious_tools": 0,
      "exfil": 0,
      "profile": "scripted_bot"
    },
    {
      "t": 50.2,
      "cmd": "ps aux | head -20",
      "ttp": "T1082",
      "recon": 9,
      "priv_esc": 0,
      "cred_access": 1,
      "lateral": 1,
      "suspicious_tools": 0,
      "exfil": 0,
      "profile": "scripted_bot"
    },
    {
      "t": 51.9,
      "cmd": "last -n 5",
      "ttp": "T1082",
      "recon": 10,
      "priv_esc": 0,
      "cred_access": 1,
      "lateral": 1,
      "suspicious_tools": 0,
      "exfil": 0,
      "profile": "scripted_bot"
    },
    {
      "t": 52.7,
      "cmd": "kernel exploit attempt (dirtypipe)",
      "ttp": "T1003",
      "recon": 10,
      "priv_esc": 0,
      "cred_access": 2,
      "lateral": 1,
      "suspicious_tools": 0,
      "exfil": 0,
      "profile": "scripted_bot"
    },
    {
      "t": 54.3,
      "cmd": "pkexec --version",
      "ttp": "T1003",
      "recon": 10,
      "priv_esc": 0,
      "cred_access": 3,
      "lateral": 1,
      "suspicious_tools": 0,
      "exfil": 0,
      "profile": "scripted_bot"
    },
    {
      "t": 57.7,
      "cmd": "arp -a",
      "ttp": "T1082",
      "recon": 11,
      "priv_esc": 0,
      "cred_access": 3,
      "lateral": 1,
      "suspicious_tools": 0,
      "exfil": 0,
      "profile": "scripted_bot"
    }
  ],
  "id": "trace_00457"
}