{
  "sophistication": 0.426,
  "profile": "scripted_bot",
  "length": 18,
  "total_time": 74.6,
  "steps": [
    {
      "t": 4.1,
      "cmd": "find / -name '*.conf' 2>/dev/null | head -5",
      "ttp": "T1082",
      "recon": 1,
      "priv_esc": 0,
      "cred_access": 0,
      "lateral": 0,
      "suspicious_tools": 0,
      "exfil": 0,
      "profile": "scripted_bot"
    },
    {
      "t": 17.8,
      "cmd": "lsadump::sam",
      "ttp": "T1003",
      "recon": 1,
      "priv_esc": 0,
      "cred_access": 1,
      "lateral": 0,
      "suspicious_tools": 0,
      "exfil": 0,
      "profile": "scripted_bot"
    },
    {
      "t": 21.0,
      "cmd": "hostname",
      "ttp": "T1082",
      "recon": 2,
      "priv_esc": 0,
      "cred_access": 1,
      "lateral": 0,
      "suspicious_tools": 0,
      "exfil": 0,
      "profile": "scripted_bot"
    },
    {
      "t": 25.8,
      "cmd": "arp -a",
      "ttp": "T1082",
      "recon": 3,
      "priv_esc": 0,
      "cred_access": 1,
      "lateral": 0,
      "suspicious_tools": 0,
      "exfil": 0,
      "profile": "scripted_bot"
    },
    {
      "t": 26.6,
      "cmd": "ls -la /home",
      "ttp": "T1082",
      "recon": 4,
      "priv_esc": 0,
      "cred_access": 1,
      "lateral": 0,
      "suspicious_tools": 0,
      "exfil": 0,
      "profile": "scripted_bot"
    },
    {
      "t": 28.7,
      "cmd": "id",
      "ttp": "T1082",
      "recon": 5,
      "priv_esc": 0,
      "cred_access": 1,
      "lateral": 0,
      "suspicious_tools": 0,
      "exfil": 0,
      "profile": "scripted_bot"
    },
    {
      "t": 29.5,
      "cmd": "cat /proc/version",
      "ttp": "T1082",
      "recon": 6,
      "priv_esc": 0,
      "cred_access": 1,
      "lateral": 0,
      "suspicious_tools": 0,
      "exfil": 0,
      "profile": "scripted_bot"
    },
    {
      "t": 33.2,
      "cmd": "pkexec --version",
      "ttp": "T1003",
      "recon": 6,
      "priv_esc": 0,
      "cred_access": 2,
      "lateral": 0,
      "suspicious_tools": 0,
      "exfil": 0,
      "profile": "scripted_bot"
    },
    {
      "t": 44.0,
      "cmd": "ps aux | head -20",
      "ttp": "T1082",
      "recon": 7,
      "priv_esc": 0,
      "cred_access": 2,
      "lateral": 0,
      "suspicious_tools": 0,
      "exfil": 0,
      "profile": "scripted_bot"
    },
    {
      "t": 48.2,
      "cmd": "id",
      "ttp": "T1082",
      "recon": 8,
      "priv_esc": 0,
      "cred_access": 2,
      "lateral": 0,
      "suspicious_tools": 0,
      "exfil": 0,
      "profile": "scripted_bot"
    },
    {
      "t": 49.0,
      "cmd": "find / -name '*.conf' 2>/dev/null | head -5",
      "ttp": "T1082",
      "recon": 9,
      "priv_esc": 0,
      "cred_access": 2,
      "lateral": 0,
      "suspicious_tools": 0,
      "exfil": 0,
      "profile": "scripted_bot"
    },
    {
      "t": 50.6,
      "cmd": "arp -a",
      "ttp": "T1082",
      "recon": 10,
      "priv_esc": 0,
      "cred_access": 2,
      "lateral": 0,
      "suspicious_tools": 0,
      "exfil": 0,
      "profile": "scripted_bot"
    },
    {
      "t": 53.7,
      "cmd": "find / -perm -4000 2>/dev/null",
      "ttp": "T1003",
      "recon": 10,
      "priv_esc": 0,
      "cred_access": 3,
      "lateral": 0,
      "suspicious_tools": 0,
      "exfil": 0,
      "profile": "scripted_bot"
    },
    {
      "t": 55.7,
      "cmd": "pkexec --version",
      "ttp": "T1003",
      "recon": 10,
      "priv_esc": 0,
      "cred_access": 4,
      "lateral": 0,
      "suspicious_tools": 0,
      "exfil": 0,
      "profile": "scripted_bot"
    },
    {
      "t": 62.7,
      "cmd": "ss -tuln",
      "ttp": "T1082",
      "recon": 11,
      "priv_esc": 0,
      "cred_access": 4,
      "lateral": 0,
      "suspicious_tools": 0,
      "exfil": 0,
      "profile": "scripted_bot"
    },
    {
      "t": 69.2,
      "cmd": "ip addr",
      "ttp": "T1082",
      "recon": 12,
      "priv_esc": 0,
      "cred_access": 4,
      "lateral": 0,
      "suspicious_tools": 0,
      "exfil": 0,
      "profile": "scripted_bot"
    },
    {
      "t": 72.8,
      "cmd": "cat /root/.aws/credentials",
      "ttp": "T1003",
      "recon": 12,
      "priv_esc": 0,
      "cred_access": 5,
      "lateral": 0,
      "suspicious_tools": 0,
      "exfil": 0,
      "profile": "scripted_bot"
    },
    {
      "t": 74.6,
      "cmd": "ls -la /home",
      "ttp": "T1082",
      "recon": 13,
      "priv_esc": 0,
      "cred_access": 5,
      "lateral": 0,
      "suspicious_tools": 0,
      "exfil": 0,
      "profile": "scripted_bot"
    }
  ],
  "id": "trace_00139"
}